metascrapy/Metadata.py
metascrapy/__init__.py
metascrapy-0.4.dist-info/DESCRIPTION.rst
metascrapy-0.4.dist-info/METADATA
metascrapy-0.4.dist-info/RECORD
metascrapy-0.4.dist-info/WHEEL
metascrapy-0.4.dist-info/metadata.json
metascrapy-0.4.dist-info/top_level.txt
