Metadata-Version: 2.0
Name: metascrapy
Version: 0.4
Summary: Scrapes meta data from a link with python
Home-page: https://github.com/bowsplinter/metascrapy
Author: Vivek Kalyan
Author-email: vivekkalyansk@gmail.com
License: MIT
Platform: UNKNOWN
Requires-Dist: requests
Requires-Dist: beautifulsoup4
